Metadata-Version: 2.1
Name: hitbtc-wss
Version: 1.0.6
Summary: HitBTC Websocket API Client
Home-page: https://github.com/mellertson/hitbtc
Author: Mike Ellertson
Author-email: mdellertson@gmail.com
License: UNKNOWN
Platform: UNKNOWN
Classifier: Programming Language :: Python :: 3 :: Only
